{
  "appPageId" : "72b57a22-ba86-4b44-8197-7def42d7cf21",
  "componentName" : "siteforce:sldsOneColLayout",
  "dataProviders" : [ ],
  "id" : "779fa792-7eb3-4df8-8cdc-fead3fcd90b6",
  "label" : "Too Many Requests",
  "regions" : [ {
    "components" : [ {
      "componentAttributes" : {
        "richTextValue" : "<div style='display: flex; align-items: center; flex-direction: column; margin: 60px 25px 30px 25px;'><div style='background-image: url(/sfsites/assets/Images/tooManyRequests/tooManyRequests.svg); background-size: contain; height: 350px; width: 100%; background-repeat: no-repeat; background-position: center;'></div></div><div style='margin: 0 25px; text-align: center;'><h1 class='slds-text-heading_large'>Looks like the site is experiencing higher than usual demand…</h1><p class='slds-text-heading_small'>Don't go anywhere. We'll redirect you in a moment.</p></div>"
      },
      "componentName" : "forceCommunity:htmlBlock",
      "id" : "130c89b0-9c23-44df-8414-3cd9da20ad58",
      "renderPriority" : "NEUTRAL",
      "renditionMap" : { },
      "type" : "component"
    }, {
      "componentAttributes" : { },
      "componentName" : "forceCommunity:autoRefresh",
      "id" : "224a0752-3de5-4593-b99f-df3a13f65376",
      "renderPriority" : "NEUTRAL",
      "renditionMap" : { },
      "type" : "component"
    } ],
    "id" : "705041f3-d708-4cd4-a30e-225be448bc43",
    "regionName" : "content",
    "type" : "region"
  } ],
  "themeLayoutType" : "ServiceNotAvailable",
  "type" : "view",
  "viewType" : "too-many-requests"
}